gendiff/__init__.py
gendiff/difference_finder.py
gendiff/engine.py
gendiff/file_reader.py
gendiff/formatter/__init__.py
gendiff/formatter/json.py
gendiff/formatter/plain.py
gendiff/formatter/stylish.py
gendiff/scripts/__init__.py
gendiff/scripts/gendiff.py
weii3hai_gendiff-0.1.1.dist-info/entry_points.txt
weii3hai_gendiff-0.1.1.dist-info/WHEEL
weii3hai_gendiff-0.1.1.dist-info/METADATA
weii3hai_gendiff-0.1.1.dist-info/RECORD
